proofreading_cli/__init__.py
proofreading_cli/api_client.py
proofreading_cli/cli.py
proofreading_cli/common.py
proofreading_cli/config/search_dimension_maping.toml
proofreading_cli/config/settings.toml
proofreading_cli/config.py
proofreading_cli/constants.py
proofreading_cli/inference_server_client.py
proofreading_cli/mapper.py
proofreading_cli/paths.py
proofreading_cli/utils.py
proofreading_cli-1.0.5.dist-info/METADATA
proofreading_cli-1.0.5.dist-info/WHEEL
proofreading_cli-1.0.5.dist-info/entry_points.txt
proofreading_cli-1.0.5.dist-info/RECORD
